pycounts_marr/.ipynb_checkpoints/plotting-checkpoint.py
pycounts_marr/.ipynb_checkpoints/pycounts_marr-checkpoint.py
pycounts_marr/__init__.py
pycounts_marr/plotting.py
pycounts_marr/pycounts_marr.py
pycounts_marr-0.1.0.dist-info/LICENSE
pycounts_marr-0.1.0.dist-info/WHEEL
pycounts_marr-0.1.0.dist-info/METADATA
pycounts_marr-0.1.0.dist-info/RECORD
